{
  "_comment": "Hunting regions with spawns. Spawn rates should total ~100 per region. Only Gen 1 species.",

  "regions": [
    {
      "id": "meadow-valley",
      "name": "Meadow Valley",
      "description": "A peaceful valley with gentle creatures",
      "difficulty": "easy",
      "energyCost": 5,
      "coinsCost": 0,
      "unlockLevel": 1,
      "imageUrl": "/regions/meadow-valley.png",
      "spawns": [
        { "species": "Rattata", "spawnRate": 30, "rarity": "common", "minLevel": 1, "maxLevel": 5 },
        { "species": "Pidgey", "spawnRate": 25, "rarity": "common", "minLevel": 2, "maxLevel": 6 },
        { "species": "Caterpie", "spawnRate": 20, "rarity": "common", "minLevel": 3, "maxLevel": 7 },
        { "species": "Oddish", "spawnRate": 15, "rarity": "uncommon", "minLevel": 4, "maxLevel": 8 },
        { "species": "Pichu", "spawnRate": 8, "rarity": "uncommon", "minLevel": 5, "maxLevel": 8 },
        { "species": "Eevee", "spawnRate": 2, "rarity": "rare", "minLevel": 5, "maxLevel": 10 }
      ]
    },
    {
      "id": "forest-grove",
      "name": "Forest Grove",
      "description": "Dense forest teeming with grass and bug types",
      "difficulty": "medium",
      "energyCost": 8,
      "coinsCost": 100,
      "unlockLevel": 5,
      "imageUrl": "/regions/forest-grove.png",
      "spawns": [
        { "species": "Oddish", "spawnRate": 25, "rarity": "common", "minLevel": 8, "maxLevel": 12 },
        { "species": "Caterpie", "spawnRate": 20, "rarity": "common", "minLevel": 8, "maxLevel": 12 },
        { "species": "Bulbasaur", "spawnRate": 20, "rarity": "uncommon", "minLevel": 10, "maxLevel": 14 },
        { "species": "Scyther", "spawnRate": 15, "rarity": "rare", "minLevel": 12, "maxLevel": 15 },
        { "species": "Growlithe", "spawnRate": 12, "rarity": "uncommon", "minLevel": 10, "maxLevel": 14 },
        { "species": "Pikachu", "spawnRate": 8, "rarity": "uncommon", "minLevel": 10, "maxLevel": 14 }
      ]
    },
    {
      "id": "volcanic-peak",
      "name": "Volcanic Peak",
      "description": "A scorching mountain where fire types thrive",
      "difficulty": "hard",
      "energyCost": 10,
      "coinsCost": 300,
      "unlockLevel": 10,
      "imageUrl": "/regions/volcanic-peak.png",
      "spawns": [
        { "species": "Vulpix", "spawnRate": 28, "rarity": "common", "minLevel": 12, "maxLevel": 16 },
        { "species": "Growlithe", "spawnRate": 25, "rarity": "common", "minLevel": 13, "maxLevel": 17 },
        { "species": "Charmander", "spawnRate": 20, "rarity": "uncommon", "minLevel": 14, "maxLevel": 18 },
        { "species": "Machop", "spawnRate": 15, "rarity": "uncommon", "minLevel": 14, "maxLevel": 18 },
        { "species": "Charmeleon", "spawnRate": 10, "rarity": "rare", "minLevel": 16, "maxLevel": 20 },
        { "species": "Arcanine", "spawnRate": 2, "rarity": "epic", "minLevel": 18, "maxLevel": 22 }
      ]
    },
    {
      "id": "crystal-lake",
      "name": "Crystal Lake",
      "description": "A serene lake where water types gather",
      "difficulty": "hard",
      "energyCost": 10,
      "coinsCost": 300,
      "unlockLevel": 10,
      "imageUrl": "/regions/crystal-lake.png",
      "spawns": [
        { "species": "Magikarp", "spawnRate": 28, "rarity": "common", "minLevel": 12, "maxLevel": 16 },
        { "species": "Psyduck", "spawnRate": 25, "rarity": "common", "minLevel": 13, "maxLevel": 17 },
        { "species": "Squirtle", "spawnRate": 20, "rarity": "uncommon", "minLevel": 14, "maxLevel": 18 },
        { "species": "Wartortle", "spawnRate": 15, "rarity": "rare", "minLevel": 16, "maxLevel": 20 },
        { "species": "Dratini", "spawnRate": 10, "rarity": "rare", "minLevel": 15, "maxLevel": 20 },
        { "species": "Gyarados", "spawnRate": 2, "rarity": "epic", "minLevel": 20, "maxLevel": 25 }
      ]
    },
    {
      "id": "thunder-plains",
      "name": "Thunder Plains",
      "description": "Stormy plains crackling with electric energy",
      "difficulty": "expert",
      "energyCost": 12,
      "coinsCost": 500,
      "unlockLevel": 15,
      "imageUrl": "/regions/thunder-plains.png",
      "spawns": [
        { "species": "Pikachu", "spawnRate": 25, "rarity": "common", "minLevel": 15, "maxLevel": 20 },
        { "species": "Electabuzz", "spawnRate": 20, "rarity": "uncommon", "minLevel": 18, "maxLevel": 22 },
        { "species": "Gastly", "spawnRate": 20, "rarity": "uncommon", "minLevel": 16, "maxLevel": 20 },
        { "species": "Haunter", "spawnRate": 15, "rarity": "rare", "minLevel": 20, "maxLevel": 25 },
        { "species": "Jolteon", "spawnRate": 10, "rarity": "rare", "minLevel": 20, "maxLevel": 25 },
        { "species": "Raichu", "spawnRate": 8, "rarity": "rare", "minLevel": 22, "maxLevel": 28 },
        { "species": "Gengar", "spawnRate": 2, "rarity": "epic", "minLevel": 25, "maxLevel": 30 }
      ]
    },
    {
      "id": "dragons-den",
      "name": "Dragon's Den",
      "description": "A hidden cave where legendary Pokemon are rumored to dwell",
      "difficulty": "legendary",
      "energyCost": 15,
      "coinsCost": 1000,
      "unlockLevel": 25,
      "imageUrl": "/regions/dragons-den.png",
      "spawns": [
        { "species": "Dratini", "spawnRate": 30, "rarity": "uncommon", "minLevel": 25, "maxLevel": 30 },
        { "species": "Dragonair", "spawnRate": 25, "rarity": "rare", "minLevel": 28, "maxLevel": 35 },
        { "species": "Machamp", "spawnRate": 15, "rarity": "rare", "minLevel": 30, "maxLevel": 38 },
        { "species": "Dragonite", "spawnRate": 15, "rarity": "epic", "minLevel": 35, "maxLevel": 45 },
        { "species": "Mewtwo", "spawnRate": 3, "rarity": "legendary", "minLevel": 50, "maxLevel": 60 },
        { "species": "Mew", "spawnRate": 2, "rarity": "legendary", "minLevel": 50, "maxLevel": 60 }
      ]
    }
  ]
}
